pytest_mesh/__init__.py
pytest_mesh/db.py
pytest_mesh/main.py
pytest_mesh/allure/bin/allure
pytest_mesh/allure/bin/allure.bat
pytest_mesh/allure/config/allure-cucumber.yml
pytest_mesh/allure/config/allure-junit.yml
pytest_mesh/allure/config/allure.yml
pytest_mesh/allure/lib/allure-commandline-2.18.1.jar
pytest_mesh/allure/lib/allure-generator-2.18.1.jar
pytest_mesh/allure/lib/allure-model-2.18.0.jar
pytest_mesh/allure/lib/allure-plugin-api-2.18.1.jar
pytest_mesh/allure/lib/allure1-model-1.0.jar
pytest_mesh/allure/lib/annotations-15.0.jar
pytest_mesh/allure/lib/commons-beanutils-1.9.4.jar
pytest_mesh/allure/lib/commons-codec-1.11.jar
pytest_mesh/allure/lib/commons-collections-3.2.2.jar
pytest_mesh/allure/lib/commons-collections4-4.2.jar
pytest_mesh/allure/lib/commons-io-2.11.0.jar
pytest_mesh/allure/lib/commons-lang3-3.12.0.jar
pytest_mesh/allure/lib/commons-logging-1.2.jar
pytest_mesh/allure/lib/commons-text-1.3.jar
pytest_mesh/allure/lib/flexmark-0.62.2.jar
pytest_mesh/allure/lib/flexmark-ext-tables-0.62.2.jar
pytest_mesh/allure/lib/flexmark-util-0.62.2.jar
pytest_mesh/allure/lib/flexmark-util-ast-0.62.2.jar
pytest_mesh/allure/lib/flexmark-util-builder-0.62.2.jar
pytest_mesh/allure/lib/flexmark-util-collection-0.62.2.jar
pytest_mesh/allure/lib/flexmark-util-data-0.62.2.jar
pytest_mesh/allure/lib/flexmark-util-dependency-0.62.2.jar
pytest_mesh/allure/lib/flexmark-util-format-0.62.2.jar
pytest_mesh/allure/lib/flexmark-util-html-0.62.2.jar
pytest_mesh/allure/lib/flexmark-util-misc-0.62.2.jar
pytest_mesh/allure/lib/flexmark-util-options-0.62.2.jar
pytest_mesh/allure/lib/flexmark-util-sequence-0.62.2.jar
pytest_mesh/allure/lib/flexmark-util-visitor-0.62.2.jar
pytest_mesh/allure/lib/freemarker-2.3.31.jar
pytest_mesh/allure/lib/httpclient-4.5.13.jar
pytest_mesh/allure/lib/httpcore-4.4.13.jar
pytest_mesh/allure/lib/jackson-annotations-2.13.3.jar
pytest_mesh/allure/lib/jackson-core-2.13.3.jar
pytest_mesh/allure/lib/jackson-databind-2.13.3.jar
pytest_mesh-1.0.35.dist-info/METADATA
pytest_mesh-1.0.35.dist-info/WHEEL
pytest_mesh-1.0.35.dist-info/entry_points.txt
pytest_mesh-1.0.35.dist-info/top_level.txt
pytest_mesh-1.0.35.dist-info/RECORD
