Metadata-Version: 2.1
Name: pytest-mesh
Version: 1.0.35
Summary: pytest_mesh插件
Home-page: UNKNOWN
Author: zhaojiajun
Author-email: zhaojiajun@baicizhan.com
License: UNKNOWN
Platform: UNKNOWN
Requires-Dist: autodoraemon (==1.0.8)
Requires-Dist: pytest (==7.1.2)
Requires-Dist: allure-pytest (==2.9.45)
Requires-Dist: SQLAlchemy (==1.4.39)
